yledl/__init__.py
yledl/__main__.py
yledl/areena_api.py
yledl/areena_extractors.py
yledl/areena_playlist_parser.py
yledl/backends.py
yledl/clip.py
yledl/downloader.py
yledl/errors.py
yledl/exitcodes.py
yledl/extractors.py
yledl/ffmpeg.py
yledl/geolocation.py
yledl/http.py
yledl/io.py
yledl/kaltura.py
yledl/localization.py
yledl/play_list_data.py
yledl/streamfilters.py
yledl/streamflavor.py
yledl/streamprobe.py
yledl/subtitles.py
yledl/timestamp.py
yledl/titleformatter.py
yledl/utils.py
yledl/version.py
yledl/yledl.py
yle_dl-20250730.dist-info/entry_points.txt
yle_dl-20250730.dist-info/licenses/COPYING
yle_dl-20250730.dist-info/WHEEL
yle_dl-20250730.dist-info/METADATA
yle_dl-20250730.dist-info/RECORD
