Metadata-Version: 2.4
Name: yle-dl
Version: 20250730
Summary: Download videos from Yle servers
Author-email: Antti Ajanki <antti.ajanki@iki.fi>
Requires-Python: >=3.8
License-Expression: GPL-3.0-or-later
Classifier: Development Status :: 5 - Production/Stable
Classifier: Environment :: Console
Classifier: Intended Audience :: End Users/Desktop
Classifier: Operating System :: OS Independent
Classifier: Programming Language :: Python
Classifier: Programming Language :: Python :: 3
Classifier: Programming Language :: Python :: 3.8
Classifier: Programming Language :: Python :: 3.9
Classifier: Programming Language :: Python :: 3.10
Classifier: Programming Language :: Python :: 3.11
Classifier: Programming Language :: Python :: 3.12
Classifier: Programming Language :: Python :: 3.13
Classifier: Topic :: Internet
Classifier: Topic :: Multimedia :: Video
License-File: COPYING
Requires-Dist: requests
Requires-Dist: lxml
Requires-Dist: ConfigArgParse >= 0.13.0
Requires-Dist: psutil ; extra == "extra"
Requires-Dist: xattr ; extra == "extra" and (sys_platform != "win32")
Requires-Dist: pytest ; extra == "test"
Project-URL: Home, https://aajanki.github.io/yle-dl/
Project-URL: Source, https://github.com/aajanki/yle-dl/
Project-URL: changelog, https://github.com/aajanki/yle-dl/blob/master/ChangeLog
Project-URL: issues, https://github.com/aajanki/yle-dl/issues
Provides-Extra: extra
Provides-Extra: test
